discrete_frenet_solver/__init__.py
discrete_frenet_solver/solver.py
discrete_frenet_solver-0.1.0.dist-info/METADATA
discrete_frenet_solver-0.1.0.dist-info/WHEEL
discrete_frenet_solver-0.1.0.dist-info/licenses/LICENSE
discrete_frenet_solver-0.1.0.dist-info/RECORD
