Metadata-Version: 2.3
Name: discrete-frenet-solver
Version: 0.1.0
Summary: A package for solving discrete Frenet frames with numerical corrections
Project-URL: Homepage, https://github.com/ShixuanGu/DiscreteFrenetSolver
Project-URL: Bug Tracker, https://github.com/ShixuanGu/DiscreteFrenetSolver/issues
Author-email: Your Name <your.email@example.com>
License-File: LICENSE
Classifier: License :: OSI Approved :: MIT License
Classifier: Operating System :: OS Independent
Classifier: Programming Language :: Python :: 3
Requires-Python: >=3.7
Requires-Dist: numpy
